uvllang/__init__.py
uvllang/cli.py
uvllang/main.py
uvllang/uvl_custom_lexer.py
uvllang/uvl_python_lexer.py
uvllang/uvl_python_parser.py
uvllang/uvl_python_parser_listener.py
uvllang-0.1.2.dist-info/licenses/LICENSE
uvllang-0.1.2.dist-info/METADATA
uvllang-0.1.2.dist-info/WHEEL
uvllang-0.1.2.dist-info/entry_points.txt
uvllang-0.1.2.dist-info/top_level.txt
uvllang-0.1.2.dist-info/RECORD
