Metadata-Version: 2.4
Name: uvllang
Version: 0.1.2
Summary: Parser for Universal Variability Language (UVL) with CNF conversion support
Author-email: h3ssto <tobias.hess@variability.dev>, UVL Team <jagalindo@us.es>
License-Expression: LGPL-3.0-or-later
Classifier: Programming Language :: Python :: 3
Classifier: Operating System :: OS Independent
Requires-Python: >=3.0
License-File: LICENSE
Requires-Dist: antlr4-python3-runtime==4.13.1
Requires-Dist: sympy>=1.12
Requires-Dist: python-sat>=0.1.8.dev13
Provides-Extra: dev
Requires-Dist: pytest>=7.0; extra == "dev"
Requires-Dist: antlr4-tools>=0.2.0; extra == "dev"
Dynamic: license-file
